horizon_hwm_store/VERSION
horizon_hwm_store/__init__.py
horizon_hwm_store/horizon_hwm_store.py
horizon_hwm_store/py.typed
horizon_hwm_store/version.py
horizon_hwm_store-1.1.4.dist-info/licenses/LICENSE.txt
horizon_hwm_store-1.1.4.dist-info/METADATA
horizon_hwm_store-1.1.4.dist-info/WHEEL
horizon_hwm_store-1.1.4.dist-info/entry_points.txt
horizon_hwm_store-1.1.4.dist-info/top_level.txt
horizon_hwm_store-1.1.4.dist-info/RECORD
