Metadata-Version: 2.4
Name: horizon-hwm-store
Version: 1.1.4
Summary: onETL Plugin for Horizon store
Home-page: https://github.com/MobileTeleSystems/horizon-hwm-store
Author: DataOps.ETL Team
Author-email: onetools@mts.ru
License: Apache-2.0
Project-URL: Documentation, https://horizon-hwm-store.readthedocs.io/
Project-URL: Source, https://github.com/MobileTeleSystems/horizon-hwm-store
Project-URL: CI/CD, https://github.com/MobileTeleSystems/horizon-hwm-store/actions
Project-URL: Tracker, https://github.com/MobileTeleSystems/horizon-hwm-store/issues
Keywords: ETL,Horizon,HWM
Classifier: Development Status :: 5 - Production/Stable
Classifier: Intended Audience :: Developers
Classifier: License :: OSI Approved :: Apache Software License
Classifier: Operating System :: OS Independent
Classifier: Programming Language :: Python :: 3 :: Only
Classifier: Programming Language :: Python :: 3.7
Classifier: Programming Language :: Python :: 3.8
Classifier: Programming Language :: Python :: 3.8
Classifier: Programming Language :: Python :: 3.9
Classifier: Programming Language :: Python :: 3.10
Classifier: Programming Language :: Python :: 3.11
Classifier: Programming Language :: Python :: 3.12
Classifier: Programming Language :: Python :: 3.13
Classifier: Topic :: Software Development :: Libraries
Classifier: Typing :: Typed
Requires-Python: >=3.7
License-File: LICENSE.txt
Requires-Dist: data-horizon[client-sync]<1.2,>=1.0
Requires-Dist: etl-entities<2.7,>=2.1
Dynamic: author
Dynamic: author-email
Dynamic: classifier
Dynamic: description
Dynamic: description-content-type
Dynamic: home-page
Dynamic: keywords
Dynamic: license
Dynamic: license-file
Dynamic: project-url
Dynamic: requires-dist
Dynamic: requires-python
Dynamic: summary
